{
  "id": "061147741b4c30fe4eb83c4bd96527c8",
  "title": "Moto Racer 4 – v1.5 + All DLCs + Multiplayer",
  "url": "https://fitgirl-repacks.site/moto-racer-4/",
  "provider": "fitgirl",
  "cover_url": "http://s01.riotpixels.net/data/53/b4/53b413ca-acf0-4b4c-8147-dd2325a4d777.jpg",
  "original_size": "5.8 GB",
  "repack_size": "2.5 GB",
  "genres": [
    "Racing",
    "Third-person",
    "3D",
    "Motorcycles"
  ],
  "magnets": [
    "magnet:?xt=urn:btih:3123103559DAB6DA76AA78BCF4E8E600F6B0BDED",
    "magnet:?xt=urn:btih:98af2f9908075ff3cc23427937d68f4df9ee4a5b&dn=rutor.info_Moto+Racer+4%3A+Deluxe+Edition+%5Bv+1.5+%2B+6+DLC%5D+%282016%29+PC+%7C+RePack+%D0%BE%D1%82+FitGirl&tr=udp://opentor.org:2710&tr=udp://opentor.org:2710&tr=http://retracker.local/announce",
    "magnet:?xt=urn:btih:2ee5c3983a197b90393f29272deab888e6f1a77b&dn=Moto+Racer+4+%5BFitGirl+Repack%5D+TAP&tr=retracker.local/announce"
  ]
}