{
  "id": "076f8ccfc72278abd2749b912151daf2",
  "title": "Tales Beyond The Tomb: Route 86",
  "url": "https://fitgirl-repacks.site/tales-beyond-the-tomb-route-86/",
  "provider": "fitgirl",
  "cover_url": "https://i5.imageban.ru/out/2025/08/31/aafb8bbc26e7cd82b5e14c501d7accd7.jpg",
  "original_size": "6.4 GB",
  "repack_size": "3.6 GB",
  "genres": [
    "Stealth",
    "Exploration",
    "Horror",
    "3D",
    "First-person"
  ],
  "magnets": [
    "magnet:?xt=urn:btih:79321B00CB7D651C7BD46B1B482B98E1FD19927E&dn=Tales+Beyond+The+Tomb%3A+Route+86+%28MULTi5%29+%5BFitGirl+Repack%5D&tr=udp%3A%2F%2Ftracker.torrent.eu.org%3A451%2Fannounce&tr=udp%3A%2F%2Ftracker.theoks.net%3A6969%2Fannounce&tr=udp%3A%2F%2Ftracker.ccp.ovh%3A6969%2Fannounce&tr=udp%3A%2F%2Ftracker.opentrackr.org%3A1337%2Fannounce&tr=http%3A%2F%2Ftracker.opentrackr.org%3A1337%2Fannounce&tr=udp%3A%2F%2Fopen.stealth.si%3A80%2Fannounce&tr=https%3A%2F%2Ftracker.tamersunion.org%3A443%2Fannounce&tr=udp%3A%2F%2Fexplodie.org%3A6969%2Fannounce&tr=http%3A%2F%2Ftracker.bt4g.com%3A2095%2Fannounce&tr=udp%3A%2F%2Fbt2.archive.org%3A6969%2Fannounce&tr=udp%3A%2F%2Fbt1.archive.org%3A6969%2Fannounce&tr=udp%3A%2F%2Ftracker.filemail.com%3A6969%2Fannounce&tr=udp%3A%2F%2Ftracker1.bt.moack.co.kr%3A80%2Fannounce&tr=http%3A%2F%2Fopen.acgnxtracker.com%3A80%2Fannounce&tr=udp%3A%2F%2Ftracker.opentrackr.org%3A1337%2Fannounce&tr=http%3A%2F%2Ftracker.openbittorrent.com%3A80%2Fannounce&tr=udp%3A%2F%2Fopentracker.i2p.rocks%3A6969%2Fannounce&tr=udp%3A%2F%2Ftracker.internetwarriors.net%3A1337%2Fannounce&tr=udp%3A%2F%2Ftracker.leechers-paradise.org%3A6969%2Fannounce&tr=udp%3A%2F%2Fcoppersurfer.tk%3A6969%2Fannounce&tr=udp%3A%2F%2Ftracker.zer0day.to%3A1337%2Fannounce"
  ]
}