{
  "id": "213eb07785ecfff20b23d5b5806af5d0",
  "title": "Mortal Kombat XL",
  "url": "https://fitgirl-repacks.site/mortal-kombat-xl/",
  "provider": "fitgirl",
  "cover_url": "http://s01.riotpixels.net/data/12/28/122897d9-b1df-41fd-bf25-3d3309fe3db5.jpg",
  "original_size": "38.8 GB",
  "repack_size": "from 23 GB [Selective Download]",
  "genres": [
    "Arcade",
    "Fighting",
    "Side",
    "3D"
  ],
  "magnets": [
    "magnet:?xt=urn:btih:343b136b720051874ef414cdbdbada199350b305",
    "magnet:?xt=urn:btih:8f49d726d920107cc90a2777ddcfdf2b5441fe0d&dn=rutor.info_Mortal+Kombat+XL+%5Bv.0.305-05.125430.1%5D+%282016%29+PC+%7C+RePack+%D0%BE%D1%82+FitGirl&tr=udp://opentor.org:2710&tr=udp://opentor.org:2710&tr=http://retracker.local/announce"
  ]
}