{
  "id": "2fa71c225ae21ab196acba9e3ceda802",
  "title": "Lantern",
  "url": "https://fitgirl-repacks.site/lantern/",
  "provider": "fitgirl",
  "cover_url": "http://s01.riotpixels.net/data/67/cd/67cda2a4-ba07-48b1-bdbc-e02aadcfeefb.jpg",
  "original_size": "1 GB",
  "repack_size": "638 MB",
  "genres": [
    "Exploration",
    "Third-person",
    "3D"
  ],
  "magnets": [
    "magnet:?xt=urn:btih:9cc2037c0514c6cc2876621e31a482eb5870537c",
    "magnet:?xt=urn:btih:9ac9fb38f9fe304e6e7dd8f58e1e9c1f5730ce5f&dn=rutor.info_Lantern+%282016%29+PC+%7C+RePack+%D0%BE%D1%82+FitGirl&tr=udp://opentor.org:2710&tr=udp://opentor.org:2710&tr=http://retracker.local/announce",
    "magnet:?xt=urn:btih:de569ca0efb0c15ec848b94d7e4a8c3f606ad394&dn=Lantern+%5BFitGirl+Repack%5D+TAP&tr=retracker.local/announce"
  ]
}