{
  "id": "354796ac6326853105df896c6d51c4ee",
  "title": "Warhammer 40,000: Chaos Gate – Daemonhunters: Grand Master Edition, Build a7bc905 (20865149) + 5 DLCs/Bonuses",
  "url": "https://fitgirl-repacks.site/warhammer-40000-chaos-gate-daemonhunters/",
  "provider": "fitgirl",
  "cover_url": "https://i4.imageban.ru/out/2026/04/08/41c2928315eb2ef313083d7cae705b62.jpg",
  "original_size": "18.6 GB",
  "repack_size": "7.1 GB",
  "genres": [
    "Strategy",
    "Action",
    "Deck-building",
    "Third-person",
    "3D"
  ],
  "magnets": [
    "magnet:?xt=urn:btih:25B630DEFE7C0052297258430FFB19E584FA3A9B&dn=Warhammer+40%2C000%3A+Chaos+Gate+-+Daemonhunters%3A+Grand+Master+Edition+%28Build+a7bc905%2F20865149+%2B+5+DLCs%2FBonuses%2C+MULTi12%29+%5BFitGirl+Hypervisor+Repack%5D&tr=udp%3A%2F%2Fopentor.net%3A6969%2Fannounce&tr=udp%3A%2F%2Ftracker.opentrackr.org%3A1337%2Fannounce&tr=udp%3A%2F%2Ftracker.torrent.eu.org%3A451%2Fannounce&tr=udp%3A%2F%2Ftracker.qu.ax%3A6969%2Fannounce&tr=udp%3A%2F%2Ftracker.fnix.net%3A6969%2Fannounce&tr=udp%3A%2F%2Fevan.im%3A6969%2Fannounce&tr=udp%3A%2F%2Fmartin-gebhardt.eu%3A25%2Fannounce&tr=https%3A%2F%2Fshahidrazi.online%3A443%2Fannounce&tr=http%3A%2F%2Fwegkxfcivgx.ydns.eu%3A80%2Fannounce&tr=http%3A%2F%2Flucke.fenesisu.moe%3A6969%2Fannounce&tr=udp%3A%2F%2Fextracker.dahrkael.net%3A6969%2Fannounce&tr=https%3A%2F%2Ftracker.alaskantf.com%3A443%2Fannounce&tr=https%3A%2F%2Ftracker.qingwa.pro%3A443%2Fannounce&tr=udp%3A%2F%2Ftracker.playground.ru%3A6969%2Fannounce&tr=udp%3A%2F%2Ftracker.opentrackr.org%3A1337%2Fannounce&tr=http%3A%2F%2Ftracker.openbittorrent.com%3A80%2Fannounce&tr=udp%3A%2F%2Fopentracker.i2p.rocks%3A6969%2Fannounce&tr=udp%3A%2F%2Ftracker.internetwarriors.net%3A1337%2Fannounce&tr=udp%3A%2F%2Ftracker.leechers-paradise.org%3A6969%2Fannounce&tr=udp%3A%2F%2Fcoppersurfer.tk%3A6969%2Fannounce&tr=udp%3A%2F%2Ftracker.zer0day.to%3A1337%2Fannounce"
  ]
}