{
  "id": "3f6439444b292369d904fc928b8bb9cc",
  "title": "Strike Vector EX",
  "url": "https://fitgirl-repacks.site/strike-vector-ex/",
  "provider": "fitgirl",
  "cover_url": "http://s01.riotpixels.net/data/5a/75/5a7591f7-56b8-46c7-87f9-d2ce7e381761.jpg",
  "original_size": "4.5 GB",
  "repack_size": "3.1 GB",
  "genres": [
    "Action",
    "Shooter",
    "Vehicular combat",
    "First-person",
    "Third-person",
    "3D"
  ],
  "magnets": [
    "magnet:?xt=urn:btih:7B9F8E46ED6EEB02AB835DF8DAFBA171A9133105",
    "magnet:?xt=urn:btih:06a3516667c1bbe8bf5c7e248b7c499a5d2d5adb&dn=Strike+Vector+EX+%5BFitGirl+Repack%5D+TAP&tr=retracker.local/announce"
  ]
}