{
  "id": "4238542edfb8858c4c296ced9e378e74",
  "title": "Operencia: The Stolen Sun – Explorer’s Edition",
  "url": "https://fitgirl-repacks.site/operencia-the-stolen-sun/",
  "provider": "fitgirl",
  "cover_url": "http://s01.riotpixels.net/data/a8/4d/a84d86db-8655-4f6e-8b18-e67a75336805.jpg",
  "original_size": "10.8 GB",
  "repack_size": "6.6/6.8 GB",
  "genres": [
    "RPG",
    "Dungeon crawl",
    "Permanent death",
    "First-person",
    "3D",
    "Real-time",
    "Turn-based"
  ],
  "magnets": [
    "magnet:?xt=urn:btih:B7ABB387B1D9B0856ECA4BF19C0B2466AD22AD4F",
    "magnet:?xt=urn:btih:b7abb387b1d9b0856eca4bf19c0b2466ad22ad4f&dn=rutor.info_Operencia%3A+The+Stolen+Sun+-+Explorer%27s+Edition+%282020%29+PC+%7C+RePack+%D0%BE%D1%82+FitGirl&tr=udp://opentor.org:2710&tr=udp://opentor.org:2710&tr=http://retracker.local/announce"
  ]
}