{
  "id": "65830ba38ab82c6dffd33c9916ef43b9",
  "title": "Fun with Ragdolls Plus – v1.2.3",
  "url": "https://fitgirl-repacks.site/fun-with-ragdolls-plus/",
  "provider": "fitgirl",
  "cover_url": "https://i6.imageban.ru/out/2026/05/21/1aad66da832c187768d2a5824ff4b168.jpg",
  "original_size": "4 GB",
  "repack_size": "2 GB",
  "genres": [
    "Arcade",
    "Jump and run",
    "Physics-based",
    "Third-person",
    "3D"
  ],
  "magnets": [
    "magnet:?xt=urn:btih:4D3DD0C7DE2E3CD60663D4EC74952C6B08FA0A4D&dn=Fun+with+Ragdolls+Plus+%28v1.2.3%29+%5BFitGirl+Repack%5D&tr=udp%3A%2F%2Ftracker.opentrackr.org%3A1337%2Fannounce&tr=udp%3A%2F%2Ftracker.torrent.eu.org%3A451%2Fannounce&tr=udp%3A%2F%2Ftracker.qu.ax%3A6969%2Fannounce&tr=udp%3A%2F%2Ftracker.fnix.net%3A6969%2Fannounce&tr=udp%3A%2F%2Fevan.im%3A6969%2Fannounce&tr=udp%3A%2F%2Fmartin-gebhardt.eu%3A25%2Fannounce&tr=https%3A%2F%2Fshahidrazi.online%3A443%2Fannounce&tr=http%3A%2F%2Fwegkxfcivgx.ydns.eu%3A80%2Fannounce&tr=http%3A%2F%2Flucke.fenesisu.moe%3A6969%2Fannounce&tr=udp%3A%2F%2Fextracker.dahrkael.net%3A6969%2Fannounce&tr=https%3A%2F%2Ftracker.alaskantf.com%3A443%2Fannounce&tr=https%3A%2F%2Ftracker.qingwa.pro%3A443%2Fannounce&tr=udp%3A%2F%2Ftracker.playground.ru%3A6969%2Fannounce&tr=udp%3A%2F%2Ftracker.skynetcloud.site%3A6969%2Fannounce&tr=udp%3A%2F%2Ftracker.opentrackr.org%3A1337%2Fannounce&tr=http%3A%2F%2Ftracker.openbittorrent.com%3A80%2Fannounce&tr=udp%3A%2F%2Fopentracker.i2p.rocks%3A6969%2Fannounce&tr=udp%3A%2F%2Ftracker.internetwarriors.net%3A1337%2Fannounce&tr=udp%3A%2F%2Ftracker.leechers-paradise.org%3A6969%2Fannounce&tr=udp%3A%2F%2Fcoppersurfer.tk%3A6969%2Fannounce&tr=udp%3A%2F%2Ftracker.zer0day.to%3A1337%2Fannounce"
  ]
}