{
  "id": "89f13f08d14296131a30f8284342232c",
  "title": "Never Grave: The Witch and The Curse – Deluxe Edition, v1.2c.s0.2132120 + 2 Bonus DLCs",
  "url": "https://fitgirl-repacks.site/never-grave-the-witch-and-the-curse/",
  "provider": "fitgirl",
  "cover_url": "https://i6.imageban.ru/out/2026/03/08/5c582017823ec1f4f5e914a03882ae1e.jpg",
  "original_size": "2.5 GB",
  "repack_size": "377 MB",
  "genres": [
    "Action",
    "Adventure",
    "Platform adventure",
    "2D"
  ],
  "magnets": [
    "magnet:?xt=urn:btih:30A2C95435540DA4072227EA687459A35B55EF76&dn=Never+Grave%3A+The+Witch+and+The+Curse+-+Deluxe+Edition+%28v1.2c.s0.2132120+%2B+2+Bonus+DLCs%2C+MULTi4%29+%5BFitGirl+Repack%5D&tr=udp%3A%2F%2Ftracker.opentrackr.org%3A1337%2Fannounce&tr=udp%3A%2F%2Ftracker.torrent.eu.org%3A451%2Fannounce&tr=udp%3A%2F%2Ftracker.qu.ax%3A6969%2Fannounce&tr=udp%3A%2F%2Ftracker.fnix.net%3A6969%2Fannounce&tr=udp%3A%2F%2Fevan.im%3A6969%2Fannounce&tr=udp%3A%2F%2Fmartin-gebhardt.eu%3A25%2Fannounce&tr=https%3A%2F%2Fshahidrazi.online%3A443%2Fannounce&tr=http%3A%2F%2Fwegkxfcivgx.ydns.eu%3A80%2Fannounce&tr=http%3A%2F%2Flucke.fenesisu.moe%3A6969%2Fannounce&tr=udp%3A%2F%2Fextracker.dahrkael.net%3A6969%2Fannounce&tr=https%3A%2F%2Ftracker.alaskantf.com%3A443%2Fannounce&tr=https%3A%2F%2Ftracker.qingwa.pro%3A443%2Fannounce&tr=udp%3A%2F%2Ftracker.playground.ru%3A6969%2Fannounce&tr=udp%3A%2F%2Ftracker.skynetcloud.site%3A6969%2Fannounce&tr=udp%3A%2F%2Ftracker.opentrackr.org%3A1337%2Fannounce&tr=http%3A%2F%2Ftracker.openbittorrent.com%3A80%2Fannounce&tr=udp%3A%2F%2Fopentracker.i2p.rocks%3A6969%2Fannounce&tr=udp%3A%2F%2Ftracker.internetwarriors.net%3A1337%2Fannounce&tr=udp%3A%2F%2Ftracker.leechers-paradise.org%3A6969%2Fannounce&tr=udp%3A%2F%2Fcoppersurfer.tk%3A6969%2Fannounce&tr=udp%3A%2F%2Ftracker.zer0day.to%3A1337%2Fannounce"
  ]
}