{
  "id": "9373604cc4a62c3a1614687f7d4435be",
  "title": "Assassin’s Creed 3: Remastered + Day 1 Patch + All DLCs + AC Liberation",
  "url": "https://fitgirl-repacks.site/assassins-creed-3-remastered/",
  "provider": "fitgirl",
  "cover_url": "http://s01.riotpixels.net/data/10/5b/105b4d00-fdc7-4663-b3d8-9f08bf5d4f83.jpg",
  "original_size": "43.6 GB",
  "repack_size": "from 9.1 GB [Selective Download]",
  "genres": [
    "Action",
    "Open world",
    "Stealth",
    "Third-person",
    "3D"
  ],
  "pop_repack_yearly": true,
  "magnets": [
    "magnet:?xt=urn:btih:4E3A9BA2B7DA3AA35293CF9C0AB4D98B1845B4B4",
    "magnet:?xt=urn:btih:67dae20de219693db4f6c9b0f1d0a8e0ac8cfe38&dn=rutor.info_Assassin%27s+Creed+3%3A+Remastered+%5Bv+1.0%5D+%282019%29+PC+%7C+RePack+%D0%BE%D1%82+FitGirl&tr=udp://opentor.org:2710&tr=udp://opentor.org:2710&tr=http://retracker.local/announce"
  ]
}