{
  "id": "a1bef12dafd82a7943275f5be634fbf9",
  "title": "Motorsport Manager – v1.4.14933 + 4 DLC",
  "url": "https://fitgirl-repacks.site/motorsport-manager/",
  "provider": "fitgirl",
  "cover_url": "http://s01.riotpixels.net/data/e2/5b/e25bdb72-6e52-4b7b-b44b-f4fd4ee1acac.jpg",
  "original_size": "9.1 GB",
  "repack_size": "3.7 GB",
  "genres": [
    "Managerial",
    "Racing",
    "Sports",
    "3D"
  ],
  "magnets": [
    "magnet:?xt=urn:btih:E88F5924647D72B9F2952A498130C46664BDC0CB",
    "magnet:?xt=urn:btih:a749d8f35f66406fe7456a5030742c3fa568113a&dn=Motorsport+Manager+%5BFitGirl+Repack%5D+TAP&tr=retracker.local/announce"
  ]
}