{
  "id": "a3942e4aba82975d7633abe3d7ee1925",
  "title": "Mato Anomalies: Digital Deluxe Edition – Build 11837913 + 8 DLCs/Bonus",
  "url": "https://fitgirl-repacks.site/mato-anomalies/",
  "provider": "fitgirl",
  "cover_url": "https://i5.imageban.ru/out/2023/03/11/581cc97e43004c02c15f246e02d6eddc.jpg",
  "original_size": "8.7 GB",
  "repack_size": "from 5.8 GB [Selective Download]",
  "genres": [
    "RPG",
    "3D",
    "Cyberpunk",
    "Turn-based"
  ],
  "magnets": [
    "magnet:?xt=urn:btih:9335EE9BC3B7E11D66B6A24D13F55E47772DADB1&dn=Mato+Anomalies%3A+Digital+Deluxe+Edition+%28Build+11837913+%2B+8+DLCs%2FBonus%2C+MULTi8%29+%5BFitGirl+Repack%2C+Selective+Download+-+from+5.8+GB%5D&tr=udp%3A%2F%2Fopentor.net%3A6969&tr=udp%3A%2F%2Fopentor.org%3A2710&tr=udp%3A%2F%2F9.rarbg.me%3A2730%2Fannounce&tr=udp%3A%2F%2F9.rarbg.me%3A2770%2Fannounce&tr=udp%3A%2F%2F9.rarbg.to%3A2720%2Fannounce&tr=udp%3A%2F%2F9.rarbg.to%3A2730%2Fannounce&tr=udp%3A%2F%2F9.rarbg.to%3A2770%2Fannounce&tr=udp%3A%2F%2Fopentracker.i2p.rocks%3A6969%2Fannounce&tr=udp%3A%2F%2Ftracker.torrent.eu.org%3A451%2Fannounce&tr=https%3A%2F%2Ftracker.tamersunion.org%3A443%2Fannounce&tr=udp%3A%2F%2Fexodus.desync.com%3A6969%2Fannounce&tr=udp%3A%2F%2Ftracker.torrent.eu.org%3A451%2Fannounce&tr=http%3A%2F%2Ftracker.gbitt.info%3A80%2Fannounce&tr=http%3A%2F%2Ftracker.ccp.ovh%3A6969%2Fannounce&tr=udp%3A%2F%2Ftracker.opentrackr.org%3A1337%2Fannounce&tr=http%3A%2F%2Ftracker.openbittorrent.com%3A80%2Fannounce&tr=udp%3A%2F%2Fopentracker.i2p.rocks%3A6969%2Fannounce&tr=udp%3A%2F%2Ftracker.internetwarriors.net%3A1337%2Fannounce&tr=udp%3A%2F%2Ftracker.leechers-paradise.org%3A6969%2Fannounce&tr=udp%3A%2F%2Fcoppersurfer.tk%3A6969%2Fannounce&tr=udp%3A%2F%2Ftracker.zer0day.to%3A1337%2Fannounce"
  ]
}