{
  "id": "aa72d448e509612567d62ef5733850d9",
  "title": "The Last Citadel – v1.0.0.4.3",
  "url": "https://fitgirl-repacks.site/the-last-citadel/",
  "provider": "fitgirl",
  "cover_url": "https://i2.imageban.ru/out/2026/02/26/5c88cf49e60e37a5a2308e22a7e272a8.jpg",
  "original_size": "3.4 GB",
  "repack_size": "2.1 GB",
  "genres": [
    "Action",
    "Shooter",
    "Content randomization",
    "Third-person",
    "3D"
  ],
  "magnets": [
    "magnet:?xt=urn:btih:B78380A2C2AA09EC848ED369166AA9E76004CA4D&dn=The+Last+Citadel+%28v1.0.0.4.3%29+%5BFitGirl+Repack%5D&tr=udp%3A%2F%2Ftracker.opentrackr.org%3A1337%2Fannounce&tr=udp%3A%2F%2Ftracker.torrent.eu.org%3A451%2Fannounce&tr=udp%3A%2F%2Ftracker.qu.ax%3A6969%2Fannounce&tr=udp%3A%2F%2Ftracker.fnix.net%3A6969%2Fannounce&tr=udp%3A%2F%2Fevan.im%3A6969%2Fannounce&tr=udp%3A%2F%2Fmartin-gebhardt.eu%3A25%2Fannounce&tr=https%3A%2F%2Fshahidrazi.online%3A443%2Fannounce&tr=http%3A%2F%2Fwegkxfcivgx.ydns.eu%3A80%2Fannounce&tr=http%3A%2F%2Flucke.fenesisu.moe%3A6969%2Fannounce&tr=udp%3A%2F%2Fextracker.dahrkael.net%3A6969%2Fannounce&tr=https%3A%2F%2Ftracker.alaskantf.com%3A443%2Fannounce&tr=https%3A%2F%2Ftracker.qingwa.pro%3A443%2Fannounce&tr=udp%3A%2F%2Ftracker.playground.ru%3A6969%2Fannounce&tr=udp%3A%2F%2Ftracker.skynetcloud.site%3A6969%2Fannounce&tr=udp%3A%2F%2Ftracker.opentrackr.org%3A1337%2Fannounce&tr=http%3A%2F%2Ftracker.openbittorrent.com%3A80%2Fannounce&tr=udp%3A%2F%2Fopentracker.i2p.rocks%3A6969%2Fannounce&tr=udp%3A%2F%2Ftracker.internetwarriors.net%3A1337%2Fannounce&tr=udp%3A%2F%2Ftracker.leechers-paradise.org%3A6969%2Fannounce&tr=udp%3A%2F%2Fcoppersurfer.tk%3A6969%2Fannounce&tr=udp%3A%2F%2Ftracker.zer0day.to%3A1337%2Fannounce"
  ]
}