{
  "id": "ab127543a4a8e9c17eb04b165771857e",
  "title": "Farmer’s Father: Save the Innocence",
  "url": "https://fitgirl-repacks.site/farmers-father-save-the-innocence/",
  "provider": "fitgirl",
  "cover_url": "https://i2.imageban.ru/out/2024/04/03/1962f4a37e945e7090d8af43191801da.jpg",
  "original_size": "13.9 GB",
  "repack_size": "4.3 GB",
  "genres": [
    "Action",
    "Item crafting",
    "Open world",
    "Survival",
    "First-person",
    "3D"
  ],
  "magnets": [
    "magnet:?xt=urn:btih:0325A75011017023D8C44620A920A0E7B1DD85B0&dn=Farmer%26%23039%3Bs+Father%3A+Save+the+Innocence+%28MULTi23%29+%5BFitGirl+Repack%5D&tr=udp%3A%2F%2Fopentor.net%3A6969&tr=udp%3A%2F%2Fopentracker.i2p.rocks%3A6969%2Fannounce&tr=http%3A%2F%2Ftracker.gbitt.info%3A80%2Fannounce&tr=http%3A%2F%2Ftracker.ccp.ovh%3A6969%2Fannounce&tr=udp%3A%2F%2Ftracker.ccp.ovh%3A6969%2Fannounce&tr=udp%3A%2F%2Ftracker.torrent.eu.org%3A451%2Fannounce&tr=udp%3A%2F%2Ftracker.torrent.eu.org%3A451%2Fannounce&tr=udp%3A%2F%2Ftracker.openbittorrent.com%3A6969%2Fannounce&tr=udp%3A%2F%2Ftracker.openbittorrent.com%3A80%2Fannounce&tr=udp%3A%2F%2Fexodus.desync.com%3A6969%2Fannounce&tr=udp%3A%2F%2Ftracker.theoks.net%3A6969%2Fannounce&tr=https%3A%2F%2Ftracker.tamersunion.org%3A443%2Fannounce&tr=http%3A%2F%2Fopen.acgnxtracker.com%3A80%2Fannounce&tr=http%3A%2F%2Fopen.acgtracker.com%3A1096%2Fannounce&tr=udp%3A%2F%2Ftracker.opentrackr.org%3A1337%2Fannounce&tr=http%3A%2F%2Ftracker.openbittorrent.com%3A80%2Fannounce&tr=udp%3A%2F%2Fopentracker.i2p.rocks%3A6969%2Fannounce&tr=udp%3A%2F%2Ftracker.internetwarriors.net%3A1337%2Fannounce&tr=udp%3A%2F%2Ftracker.leechers-paradise.org%3A6969%2Fannounce&tr=udp%3A%2F%2Fcoppersurfer.tk%3A6969%2Fannounce&tr=udp%3A%2F%2Ftracker.zer0day.to%3A1337%2Fannounce",
    "magnet:?xt=urn:btih:0325a75011017023d8c44620a920a0e7b1dd85b0&dn=rutor.info_Farmer%27s+Father%3A+Save+the+Innocence+%282024%29+PC+%7C+RePack+%D0%BE%D1%82+FitGirl&tr=udp://opentor.net:6969&tr=http://retracker.local/announce"
  ]
}