{
  "id": "b0fffdcd595f833685709169ef5d1b80",
  "title": "Grimshade – v1.0.2",
  "url": "https://fitgirl-repacks.site/grimshade/",
  "provider": "fitgirl",
  "cover_url": "http://s01.riotpixels.net/data/4b/f8/4bf82bc0-62a6-4b4e-8487-a306774c4843.jpg",
  "original_size": "5.1 GB",
  "repack_size": "2.7 GB",
  "genres": [
    "RPG",
    "Strategy",
    "Tactics",
    "Isometric",
    "Turn-based"
  ],
  "magnets": [
    "magnet:?xt=urn:btih:9B8438C8A2C0F1806BD9D67EF3184FF1F625AE9A",
    "magnet:?xt=urn:btih:1ca25081e1c7c8363a525a0ad3eb00d2ec69bb5e&dn=rutor.info_Grimshade+%5Bv+1.0.2%5D+%282019%29+PC+%7C+RePack+%D0%BE%D1%82+FitGirl&tr=udp://opentor.org:2710&tr=udp://opentor.org:2710&tr=http://retracker.local/announce"
  ]
}