{
  "id": "be7f2570eb5112ff3e0816e457938c9f",
  "title": "Biped – v1.1",
  "url": "https://fitgirl-repacks.site/biped/",
  "provider": "fitgirl",
  "cover_url": "http://s01.riotpixels.net/data/4c/f3/4cf37e92-b4ad-48ad-b6a2-2549be6bd42b.jpg",
  "original_size": "3.8 GB",
  "repack_size": "from 1.4 GB [Selective Download]",
  "genres": [
    "Arcade",
    "Logic",
    "Puzzle",
    "3D"
  ],
  "magnets": [
    "magnet:?xt=urn:btih:ECF961E39CE79AD6FE56F0509466363594B7739C",
    "magnet:?xt=urn:btih:ecf961e39ce79ad6fe56f0509466363594b7739c&dn=rutor.info_Biped+%5Bv+1.1%5D+%282020%29+PC+%7C+RePack+%D0%BE%D1%82+FitGirl&tr=udp://opentor.org:2710&tr=udp://opentor.org:2710&tr=http://retracker.local/announce"
  ]
}