{
  "id": "c885c5e6804833438d0d78636e0ca06d",
  "title": "Atelier Ryza 2: Lost Legends & The Secret Fairy – Digital Deluxe Edition + 8 DLCs",
  "url": "https://fitgirl-repacks.site/atelier-ryza-2/",
  "provider": "fitgirl",
  "cover_url": "http://s01.riotpixels.net/data/30/d4/30d4f0b2-79e4-450e-b99d-ff114acab3bf.jpg",
  "original_size": "14.5 GB",
  "repack_size": "from 7.8 GB [Selective Download]",
  "genres": [
    "RPG",
    "Third-person",
    "3D",
    "Japanese"
  ],
  "magnets": [
    "magnet:?xt=urn:btih:323D3067DBD162C1996D443734A170CC0FF2B379"
  ]
}