{
  "id": "caf1aa8fac18f879313114fd68679289",
  "title": "Command & Conquer: Remastered Collection – v1.153 Build 732159",
  "url": "https://fitgirl-repacks.site/command-conquer-remastered-collection/",
  "provider": "fitgirl",
  "cover_url": "http://s01.riotpixels.net/data/07/03/0703e4e7-5244-4f70-a788-b6f7f6ae6be8.jpg",
  "original_size": "21.3 GB",
  "repack_size": "from 8.9 GB [Selective Download]",
  "genres": [
    "Strategy",
    "RTS",
    "Top-down",
    "2D"
  ],
  "magnets": [
    "magnet:?xt=urn:btih:0B73F3A40286880FB265FDC4A747830DA5E57697",
    "magnet:?xt=urn:btih:0b73f3a40286880fb265fdc4a747830da5e57697&dn=rutor.info_Command+%26amp%3B+Conquer%3A+Remastered+Collection+%5Bv+1.153+Build+732159%5D+%282020%29+PC+%7C+RePack+%D0%BE%D1%82+FitGirl&tr=udp://opentor.org:2710&tr=udp://opentor.org:2710&tr=http://retracker.local/announce"
  ]
}