{
  "id": "ce8eeebfaa16b71a91bbac8a6be1e333",
  "title": "MX vs ATV Legends: Deluxe Edition, v5.04 + 49 DLCs + Windows 7 Fix",
  "url": "https://fitgirl-repacks.site/mx-vs-atv-legends/",
  "provider": "fitgirl",
  "cover_url": "https://i2.imageban.ru/out/2022/07/03/3bbacc7176b2b4c98704eacfa7b69b9f.jpg",
  "original_size": "51.6 GB",
  "repack_size": "27.1 GB",
  "genres": [
    "Racing",
    "ATV",
    "Motorcycles",
    "3D"
  ],
  "magnets": [
    "magnet:?xt=urn:btih:5B68FFBF8CCD1A253136E985FFB4D9B591FB1996&dn=MX+vs+ATV+Legends%3A+Deluxe+Edition+%28v5.04+%2B+49+DLCs+%2B+Windows+7+Fix%2C+MULTi11%29+%5BFitGirl+Repack%5D&tr=udp%3A%2F%2Fopentor.net%3A6969%2Fannounce&tr=udp%3A%2F%2Ftracker.opentrackr.org%3A1337%2Fannounce&tr=udp%3A%2F%2Ftracker.torrent.eu.org%3A451%2Fannounce&tr=udp%3A%2F%2Ftracker.qu.ax%3A6969%2Fannounce&tr=udp%3A%2F%2Ftracker.fnix.net%3A6969%2Fannounce&tr=udp%3A%2F%2Fevan.im%3A6969%2Fannounce&tr=udp%3A%2F%2Fmartin-gebhardt.eu%3A25%2Fannounce&tr=https%3A%2F%2Fshahidrazi.online%3A443%2Fannounce&tr=http%3A%2F%2Fwegkxfcivgx.ydns.eu%3A80%2Fannounce&tr=http%3A%2F%2Flucke.fenesisu.moe%3A6969%2Fannounce&tr=udp%3A%2F%2Fextracker.dahrkael.net%3A6969%2Fannounce&tr=https%3A%2F%2Ftracker.alaskantf.com%3A443%2Fannounce&tr=https%3A%2F%2Ftracker.qingwa.pro%3A443%2Fannounce&tr=udp%3A%2F%2Ftracker.playground.ru%3A6969%2Fannounce&tr=udp%3A%2F%2Ftracker.opentrackr.org%3A1337%2Fannounce&tr=http%3A%2F%2Ftracker.openbittorrent.com%3A80%2Fannounce&tr=udp%3A%2F%2Fopentracker.i2p.rocks%3A6969%2Fannounce&tr=udp%3A%2F%2Ftracker.internetwarriors.net%3A1337%2Fannounce&tr=udp%3A%2F%2Ftracker.leechers-paradise.org%3A6969%2Fannounce&tr=udp%3A%2F%2Fcoppersurfer.tk%3A6969%2Fannounce&tr=udp%3A%2F%2Ftracker.zer0day.to%3A1337%2Fannounce",
    "magnet:?xt=urn:btih:5b68ffbf8ccd1a253136e985ffb4d9b591fb1996&dn=rutor.info_MX+vs+ATV+Legends%3A+Deluxe+Edition+%5Bv+5.04+%2B+DLCs%5D+%282022%29+PC+%7C+RePack+%D0%BE%D1%82+FitGirl&tr=udp://opentor.net:6969&tr=http://retracker.local/announce"
  ]
}