{
  "id": "d7963b20043b97aa6b48049ad150949b",
  "title": "Battlezone: Gold Edition – v1.08 + Multiplayer",
  "url": "https://fitgirl-repacks.site/battlezone-gold-edition/",
  "provider": "fitgirl",
  "cover_url": "http://s01.riotpixels.net/data/12/27/1227f7eb-116d-4067-af61-90f7171ea302.jpg",
  "original_size": "4.2 GB",
  "repack_size": "1.4 GB",
  "genres": [
    "Action",
    "Shooter",
    "First-person",
    "3D"
  ],
  "magnets": [
    "magnet:?xt=urn:btih:FC6BF0A2BA7014BC259E2EDE2C04A6DC22CC5659",
    "magnet:?xt=urn:btih:fe88ff4f15ec3da93d73ed3b260d9bb58ca7bdd2&dn=rutor.info_Battlezone+Gold+Edition+%282017%29+PC+%7C+RePack+%D0%BE%D1%82+FitGirl&tr=udp://opentor.org:2710&tr=udp://opentor.org:2710&tr=http://retracker.local/announce",
    "magnet:?xt=urn:btih:1c8bf17ecc0c3a3e42d0d2f41bfa5b9c951e7c22&dn=Battlezone+-+Gold+Edition+%5BFitGirl+Repack%5D+TAP&tr=retracker.local/announce"
  ]
}