{
  "id": "dcf55902fa3e3efe9046eb2e3ef48038",
  "title": "The Great War: Western Front – Victory Edition, Build 822194 + 2 DLC/Bonuses",
  "url": "https://fitgirl-repacks.site/the-great-war-western-front/",
  "provider": "fitgirl",
  "cover_url": "https://i2.imageban.ru/out/2025/02/03/001391c6ffd701c8017cd34340107cbe.jpg",
  "original_size": "9.2 GB",
  "repack_size": "from 6.6 GB [Selective Download]",
  "genres": [
    "Strategy",
    "Tactics",
    "World War I",
    "Isometric",
    "3D",
    "Real-time",
    "Turn-based"
  ]
}