{
  "id": "dea864d772507ab7b481294305183383",
  "title": "LEGO The Incredibles + DLC",
  "url": "https://fitgirl-repacks.site/lego-the-incredibles/",
  "provider": "fitgirl",
  "cover_url": "http://s01.riotpixels.net/data/5e/fe/5efe3d3c-4490-483a-b5aa-8c8649d15256.jpg",
  "original_size": "13.8 GB",
  "repack_size": "from 4.6 GB [Selective Download]",
  "genres": [
    "Action",
    "Third-person",
    "3D"
  ],
  "magnets": [
    "magnet:?xt=urn:btih:6A616CDA05D6529E57AD278B548AA8291B50106A",
    "magnet:?xt=urn:btih:783f0863ad89c830ae12940b3ec9336694c780fc&dn=rutor.info_LEGO+The+Incredibles+%5B1.0.0+%2B+1+DLC%5D+%282018%29+PC+%7C+RePack+%D0%BE%D1%82+FitGirl&tr=udp://opentor.org:2710&tr=udp://opentor.org:2710&tr=http://retracker.local/announce"
  ]
}