{
  "page": 73,
  "total_pages": 233,
  "items": [
    {
      "id": "4d987eccde4462714cce41af4be97b52",
      "title": "Tempest Rising: Deluxe Edition, v1.8.0+57140 + 4 DLCs/Bonuses",
      "url": "https://fitgirl-repacks.site/tempest-rising/",
      "provider": "fitgirl",
      "cover_url": "https://i1.imageban.ru/out/2025/04/18/89e353a1ec176e55209737fd72800993.jpg",
      "repack_size": "from 31.1 GB [Selective Download]"
    },
    {
      "id": "4dab1324c9ed4f407bb8d4e3b31e9baa",
      "title": "Mexico, 1921. A Deep Slumber.",
      "url": "https://fitgirl-repacks.site/mexico-1921-a-deep-slumber/",
      "provider": "fitgirl",
      "cover_url": "https://i3.imageban.ru/out/2024/10/12/4b804da3b8baccbff9674be70b982e3d.jpg",
      "repack_size": "3.3 GB"
    },
    {
      "id": "4dac60ba936ca5d9ec0ffa89418b811c",
      "title": "Sonic Racing: CrossWorlds, v1.3.1 + 7 DLCs + 12 Bonus OSTs",
      "url": "https://fitgirl-repacks.site/sonic-racing-crossworlds-pc/",
      "provider": "fitgirl",
      "cover_url": "https://i8.imageban.ru/out/2026/03/31/2a7f6d9b5b698d48bdf9c1a1718db0f8.jpg",
      "repack_size": "11.2/12.5 GB"
    },
    {
      "id": "4dcee0ff538cbfef9ecf87729ede0f87",
      "title": "All in Abyss: Judge the Fake – Digital Deluxe Edition + 3 DLCs/Bonuses",
      "url": "https://fitgirl-repacks.site/all-in-abyss-judge-the-fake/",
      "provider": "fitgirl",
      "cover_url": "https://i5.imageban.ru/out/2025/04/12/f77e87575a10505eeb85f4e429defdf4.jpg",
      "repack_size": "625/898 MB"
    },
    {
      "id": "4dda1b2a5fe3e488054d5ac6425f5051",
      "title": "The Illusion: Curse",
      "url": "https://fitgirl-repacks.site/the-illusion-curse/",
      "provider": "fitgirl",
      "cover_url": "https://i3.imageban.ru/out/2023/04/02/d04df56ddff29480f1bec8ad3eff5969.jpg",
      "repack_size": "2.8 GB"
    },
    {
      "id": "4ddbe59594058c2e09da7e6f8e57cb88",
      "title": "Bad Cheese – v1.00.035 + Bonus Artbook",
      "url": "https://fitgirl-repacks.site/bad-cheese/",
      "provider": "fitgirl",
      "cover_url": "https://i4.imageban.ru/out/2025/09/10/7fa3185237322fc7cb2b77c05ee1108e.jpg",
      "repack_size": "631/946 MB"
    },
    {
      "id": "4de018906c7eb26d9d9b45804f260e6f",
      "title": "United Assault: Battle of the Bulge",
      "url": "https://fitgirl-repacks.site/united-assault-battle-of-the-bulge/",
      "provider": "fitgirl",
      "cover_url": "https://i2.imageban.ru/out/2022/08/22/05159aa0ef9496ded4cfcc4d8220213f.jpg",
      "repack_size": "3.1 GB"
    },
    {
      "id": "4e05501616be4effb68891c56c6fbe4c",
      "title": "Out of Hands: Nightmare Collector’s Edition, v1.0.0#164 + Bonus DLC",
      "url": "https://fitgirl-repacks.site/out-of-hands/",
      "provider": "fitgirl",
      "cover_url": "https://i5.imageban.ru/out/2025/05/05/7c11ac4ac07398308d5098008e7b2d77.jpg",
      "repack_size": "947 MB/1.4 GB"
    },
    {
      "id": "4e09fccfec98ce85aa203c8e35d96d4c",
      "title": "X Rebirth – v4.10 + 2 DLCs",
      "url": "https://fitgirl-repacks.site/x-rebirth-v4-10-2-dlcs/",
      "provider": "fitgirl",
      "cover_url": "http://s01.riotpixels.net/data/b7/1e/b71e39f0-a71c-45fc-8c89-e68b84363217.jpg",
      "repack_size": "from 3.5 GB [Selective Download]"
    },
    {
      "id": "4e139f7b5e4dcb6c2088a97d996e3853",
      "title": "Kingdoms of Amalur: Reckoning – v1.0.0.2 + All DLCs",
      "url": "https://fitgirl-repacks.site/kingdoms-of-amalur-reckoning/",
      "provider": "fitgirl",
      "cover_url": "http://s01.riotpixels.net/data/5b/22/5b22c12a-07f8-43d0-a8be-07e85fab0aad.jpg",
      "repack_size": "from 5.7 GB"
    },
    {
      "id": "4e200d6304592bc030a855c1e10fdf38",
      "title": "Borderlands: Game of The Year Edition – v1.5.0 + 4 DLCs",
      "url": "https://fitgirl-repacks.site/borderlands-game-of-the-year-edition/",
      "provider": "fitgirl",
      "cover_url": "http://s01.riotpixels.net/data/46/8d/468d4de8-06e3-437e-ab01-e1722d496543.jpg",
      "repack_size": "from 5.2 GB [Selective Download]"
    },
    {
      "id": "4e2015c896ebaf0467f2e90a6430248c",
      "title": "Eisenhorn: XENOS",
      "url": "https://fitgirl-repacks.site/eisenhorn-xenos/",
      "provider": "fitgirl",
      "cover_url": "http://s01.riotpixels.net/data/f9/be/f9be4f93-6edc-42f3-b6f2-3de693834919.jpg",
      "repack_size": "5.4 GB"
    },
    {
      "id": "4e2a7b9565c1be1b57a5ee7ceb3bea21",
      "title": "The Talos Principle: Reawakened – v729654",
      "url": "https://fitgirl-repacks.site/the-talos-principle-reawakened/",
      "provider": "fitgirl",
      "cover_url": "https://i3.imageban.ru/out/2025/04/11/f59aaa83a9bbe41ce3ee08fa422323b8.jpg",
      "repack_size": "from 30.3 GB [Selective Download]"
    },
    {
      "id": "4e3d643d859a23bd50feb8f091f32867",
      "title": "Restaurats: Deluxe Edition – v0.19.0.19 + 3 DLCs/Bonuses",
      "url": "https://fitgirl-repacks.site/restaurats/",
      "provider": "fitgirl",
      "cover_url": "https://i1.imageban.ru/out/2025/11/12/a033683476c429e84c0afc045f78afd0.jpg",
      "repack_size": "2.1/2.4 GB"
    },
    {
      "id": "4e451203ef1fee8084f26774185037c3",
      "title": "How to Survive: Storm Warning Edition",
      "url": "https://fitgirl-repacks.site/how-to-survive-storm-warning-edition/",
      "provider": "fitgirl",
      "cover_url": "http://i65.fastpic.ru/big/2015/0222/27/b79a46932d5bb5e7050610ee81501727.jpg",
      "repack_size": "1,2 GB"
    },
    {
      "id": "4e5d0376cc445fe9d0d76dab8f758832",
      "title": "The Technomancer",
      "url": "https://fitgirl-repacks.site/the-technomancer/",
      "provider": "fitgirl",
      "cover_url": "http://i61.fastpic.ru/big/2016/0629/b5/7f7a725c252c94615b7cdf78aa8d75b5.jpg",
      "repack_size": "from 5.7 GB [Selective Download]"
    },
    {
      "id": "4e6aa14e7174f44e2fc38e394532ddbf",
      "title": "For The King II: Deluxe Edition – v1.12.11 + 5 DLCs/Bonuses",
      "url": "https://fitgirl-repacks.site/for-the-king-2/",
      "provider": "fitgirl",
      "cover_url": "https://i2.imageban.ru/out/2023/11/04/19774e6e5039edb79bd85295b46585f6.jpg",
      "repack_size": "4.4 GB"
    },
    {
      "id": "4e6c01a29ca6e3ed1e576dd65c2ef96c",
      "title": "Dust & Courage: Jake Bolton’s Journey",
      "url": "https://fitgirl-repacks.site/dust-and-courage-jake-boltons-journey/",
      "provider": "fitgirl",
      "cover_url": "https://i5.imageban.ru/out/2026/01/31/48006217003b34e9fce6a7bb6afadd3f.jpg",
      "repack_size": "651 MB"
    },
    {
      "id": "4e726a940fb2aa89912392faa52cc39a",
      "title": "MEGA MAN X DiVE Offline",
      "url": "https://fitgirl-repacks.site/mega-man-x-dive-offline/",
      "provider": "fitgirl",
      "cover_url": "https://i5.imageban.ru/out/2023/09/06/f41adb5ed9b785db81c58db532144c8a.jpg",
      "repack_size": "1.1 GB"
    },
    {
      "id": "4e7ecd0e32ca09521557701f4d2240d9",
      "title": "Hot Lap Racing: Deluxe Edition – v1.0.3-0cfd3d1de + Bonus Soundtrack",
      "url": "https://fitgirl-repacks.site/hot-lap-racing/",
      "provider": "fitgirl",
      "cover_url": "https://i2.imageban.ru/out/2024/07/25/51e41681fca471d215d9e2c84d95fce5.jpg",
      "repack_size": "2.8/2.9 GB"
    },
    {
      "id": "4e85b6e89c11149217e8a016b6558092",
      "title": "One True Hero – v1.0.1d",
      "url": "https://fitgirl-repacks.site/one-true-hero/",
      "provider": "fitgirl",
      "cover_url": "https://i2.imageban.ru/out/2022/10/22/d48fa4f80551ddeb975a853acc17ec46.jpg",
      "repack_size": "1.6 GB"
    },
    {
      "id": "4e8ae4c4080d6e1cf72a085f7f8f5680",
      "title": "Revenge of ILCOIN",
      "url": "https://fitgirl-repacks.site/revenge-of-ilcoin/",
      "provider": "fitgirl",
      "cover_url": "https://i1.imageban.ru/out/2023/09/11/fc746c696764e77ed2868d332619dc4d.jpg",
      "repack_size": "3.1 GB"
    },
    {
      "id": "4e8b7a276eade4317f11698faeaea3f5",
      "title": "Train World – v1.12.31 + Windows 7 Fix",
      "url": "https://fitgirl-repacks.site/train-world/",
      "provider": "fitgirl",
      "cover_url": "https://i1.imageban.ru/out/2023/09/07/7cdfc2f84e0cc71cc3439b79857d1d75.jpg",
      "repack_size": "1 GB"
    },
    {
      "id": "4e94d2481406791545a428da8a927fa8",
      "title": "ITORAH",
      "url": "https://fitgirl-repacks.site/itorah/",
      "provider": "fitgirl",
      "cover_url": "https://i6.imageban.ru/out/2022/03/22/b8c4406518fc9100b999095139de8d3b.jpg",
      "repack_size": "1.1 GB"
    },
    {
      "id": "4e96a0293252d20694c33c7a416028e6",
      "title": "There’s Something In The Ice + Windows 7 Fix",
      "url": "https://fitgirl-repacks.site/theres-something-in-the-ice/",
      "provider": "fitgirl",
      "cover_url": "https://i4.imageban.ru/out/2024/03/30/d17bfbc42297eb0f9e5eace99d10530a.jpg",
      "repack_size": "7.7 GB"
    },
    {
      "id": "4e9d3810baaf36fcd0b69863e55f35d9",
      "title": "Hyperdimension Neptunia: Re;Birth Trilogy + All DLCs",
      "url": "https://fitgirl-repacks.site/hyperdimension-neptunia-re-birth-trilogy/",
      "provider": "fitgirl",
      "cover_url": "http://s01.riotpixels.net/data/78/e0/78e0964d-b32d-47ba-8836-c63fb84f444f.jpg",
      "repack_size": "from 7.7 GB [Selective Download]"
    },
    {
      "id": "4eaa0856b246f1822cb2d23278144278",
      "title": "Crysis Remastered – v Patch 3 (BuildID 8139684) + Bonus Content",
      "url": "https://fitgirl-repacks.site/crysis-remastered/",
      "provider": "fitgirl",
      "cover_url": "https://i1.imageban.ru/out/2021/09/18/229a58c668eb23913a17c998a7445ec0.jpg",
      "repack_size": "from 10.3 GB [Selective Download]"
    },
    {
      "id": "4ebe5dd7c9bec1a435cb3667b99e31ed",
      "title": "Disharmonia",
      "url": "https://fitgirl-repacks.site/disharmonia/",
      "provider": "fitgirl",
      "cover_url": "https://i4.imageban.ru/out/2022/05/06/81f5235463dc0b716f7939ea479cf155.jpg",
      "repack_size": "976 MB"
    },
    {
      "id": "4ebea5d81fb7452e36c1dd1f20e0b72e",
      "title": "The Feud: Wild West Tactics – Build 181 (Unlimited Frontier)",
      "url": "https://fitgirl-repacks.site/the-feud-wild-west-tactics/",
      "provider": "fitgirl",
      "cover_url": "http://s01.riotpixels.net/data/0e/d7/0ed7f101-b450-406b-81d4-4d31519dc55e.jpg",
      "repack_size": "1.1 GB"
    },
    {
      "id": "4ec283fa6dde04735d62c4d7a8595dd5",
      "title": "Willy Morgan and the Curse of Bone Town",
      "url": "https://fitgirl-repacks.site/willy-morgan-and-the-curse-of-bone-town/",
      "provider": "fitgirl",
      "cover_url": "http://s01.riotpixels.net/data/4b/0d/4b0d49de-3e2b-41b0-906c-0a6288518a7b.jpg",
      "repack_size": "1.5 GB"
    }
  ]
}