{
  "page": 171,
  "total_pages": 233,
  "items": [
    {
      "id": "baadfe90f8d2f50c09d46f702878620a",
      "title": "Station to Station – v1.4.1 (4960) / Creative Mode Update",
      "url": "https://fitgirl-repacks.site/station-to-station/",
      "provider": "fitgirl",
      "cover_url": "https://i2.imageban.ru/out/2023/10/04/3bcd3ab358ba7baf165ae6b3716831f6.jpg",
      "repack_size": "1.2 GB"
    },
    {
      "id": "babb0380c06f76a525974cfacc52ccd1",
      "title": "Carmageddon: Max Damage – The U.S. Election Nightmare Special Edition",
      "url": "https://fitgirl-repacks.site/carmageddon-max-damage-u-s-election-nightmare-special-edition/",
      "provider": "fitgirl",
      "cover_url": "http://s01.riotpixels.net/data/b1/c6/b1c664f1-598a-4869-a220-a936817e18f6.jpg",
      "repack_size": "5.5 GB"
    },
    {
      "id": "bac0d84e64a808674b1d7976a2099133",
      "title": "Die Again + Bonus Soundtrack",
      "url": "https://fitgirl-repacks.site/die-again/",
      "provider": "fitgirl",
      "cover_url": "https://i1.imageban.ru/out/2024/04/17/acde2e471792c0f068979c680c88ec29.jpg",
      "repack_size": "4.1/4.2 GB"
    },
    {
      "id": "bac5d4893867124946552b7b06fe3c8d",
      "title": "BULLRING",
      "url": "https://fitgirl-repacks.site/bullring/",
      "provider": "fitgirl",
      "cover_url": "https://i4.imageban.ru/out/2024/01/29/04b0027fe43b0a78b437d0f8b13bd62f.jpg",
      "repack_size": "4.1 GB"
    },
    {
      "id": "bad14ea6d4edfb88172b01a60ff5fd3b",
      "title": "Empathy: Path of Whispers",
      "url": "https://fitgirl-repacks.site/empathy-path-whispers/",
      "provider": "fitgirl",
      "cover_url": "http://s01.riotpixels.net/data/6b/b4/6bb4d4ca-226d-4116-a90e-b99331c06fc1.jpg",
      "repack_size": "2 GB"
    },
    {
      "id": "bad4b09ee92f5fda243f2798f46f2257",
      "title": "Orcs Must Die! Deathtrap – v1.1.2 + Supporters Pack DLC",
      "url": "https://fitgirl-repacks.site/orcs-must-die-deathtrap/",
      "provider": "fitgirl",
      "cover_url": "https://i7.imageban.ru/out/2025/01/28/de268fc9053a93fda8906165c10cd7f6.jpg",
      "repack_size": "6.9 GB"
    },
    {
      "id": "badad3a53cc1db1bc36a040cec50147c",
      "title": "Quantum Break: Steam Edition – v1.0.126.0307",
      "url": "https://fitgirl-repacks.site/quantum-break-steam-edition/",
      "provider": "fitgirl",
      "cover_url": "http://s01.riotpixels.net/data/62/c1/62c1e9b4-4545-46e5-b0a6-ba08e4744f2d.jpg",
      "repack_size": "from 26.3 GB [Selective Download]"
    },
    {
      "id": "bae158ba0eecede57a169b4389b95452",
      "title": "RIDE 5: Special Edition – Build 13410226 + 16 DLCs + Windows 7 Fix",
      "url": "https://fitgirl-repacks.site/ride-5/",
      "provider": "fitgirl",
      "cover_url": "https://i2.imageban.ru/out/2023/08/26/e2484583f132a13541c25f0307e0b6d4.jpg",
      "repack_size": "26.6 GB"
    },
    {
      "id": "bae1fbaf600f9e402702ede2733c0d33",
      "title": "Star Mission: Remote Sectors – v1.0.0",
      "url": "https://fitgirl-repacks.site/star-mission-remote-sectors/",
      "provider": "fitgirl",
      "cover_url": "https://i3.imageban.ru/out/2025/06/02/07bffdf5393c8732806361933a52bde6.jpg",
      "repack_size": "4.2 GB"
    },
    {
      "id": "bae7aee8e8a00912b2c2205c4928f107",
      "title": "Warhammer 40,000: Armageddon + Untold Battles DLC",
      "url": "https://fitgirl-repacks.site/warhammer-40000-armageddon-untold-battles-dlc/",
      "provider": "fitgirl",
      "cover_url": "http://i64.fastpic.ru/big/2015/0302/6c/62868adffd52bd9fa975ba0c0cae356c.jpg",
      "repack_size": "781 MB"
    },
    {
      "id": "bb0e92aef3ea09837f52ecbf421409f4",
      "title": "COCOON",
      "url": "https://fitgirl-repacks.site/cocoon/",
      "provider": "fitgirl",
      "cover_url": "https://i5.imageban.ru/out/2023/09/30/54d4c534f32c602bed71484ca9b984e9.jpg",
      "repack_size": "581 MB"
    },
    {
      "id": "bb10713d874c50914027bad614883167",
      "title": "Pompeii: The Legacy – v1.000.6",
      "url": "https://fitgirl-repacks.site/pompeii-the-legacy/",
      "provider": "fitgirl",
      "cover_url": "https://i3.imageban.ru/out/2026/04/26/a7da925f8f5f2b17c65c6a6e037c0976.jpg",
      "repack_size": "4.1 GB"
    },
    {
      "id": "bb1086424cab91f0d4aedf580e7293e1",
      "title": "Dark Days: Devil Hunt",
      "url": "https://fitgirl-repacks.site/dark-days-devil-hunt/",
      "provider": "fitgirl",
      "cover_url": "https://i3.imageban.ru/out/2023/05/23/5d8050030956a511bf82e9b768b1fb86.jpg",
      "repack_size": "6.3 GB"
    },
    {
      "id": "bb29b73ddd83d3c91d7247d06332ed5f",
      "title": "Tales of the Shire: A The Lord of The Rings Game – v1.0 #46029",
      "url": "https://fitgirl-repacks.site/tales-of-the-shire-a-the-lord-of-the-rings-game/",
      "provider": "fitgirl",
      "cover_url": "https://i5.imageban.ru/out/2025/07/30/cccbd32a99d719fc570e2e55a5ee11c8.jpg",
      "repack_size": "1.5 GB"
    },
    {
      "id": "bb2e0dfbf725660c764bc3b61561f6b1",
      "title": "Dust Fleet – v6.0 (The Sector Assault Update)",
      "url": "https://fitgirl-repacks.site/dust-fleet/",
      "provider": "fitgirl",
      "cover_url": "https://i2.imageban.ru/out/2023/08/28/a6ad6556d291de11144e8540533eeaa5.jpg",
      "repack_size": "1.1 GB"
    },
    {
      "id": "bb2f9db86c315d58f4a7f71a2f06da19",
      "title": "Super Lucky’s Tale + DLC",
      "url": "https://fitgirl-repacks.site/super-luckys-tale-dlc/",
      "provider": "fitgirl",
      "cover_url": "http://s01.riotpixels.net/data/d7/f9/d7f9c852-6ef5-44c5-8aa7-682e5d7a3d5d.jpg",
      "repack_size": "from 3.3 GB [Selective Download]"
    },
    {
      "id": "bb33fb25acaefcb1d38137cc97d84a1c",
      "title": "God Eater: Resurrection",
      "url": "https://fitgirl-repacks.site/god-eater-resurrection/",
      "provider": "fitgirl",
      "cover_url": "http://s01.riotpixels.net/data/5a/d0/5ad07388-f996-4dee-a16e-dbc4bf4435a3.jpg",
      "repack_size": "4.7 GB"
    },
    {
      "id": "bb42d15bed6ee3bcecfe611c58613b87",
      "title": "Darksiders III – v203415_PK1_PK2 + 3 DLCs",
      "url": "https://fitgirl-repacks.site/darksiders-3/",
      "provider": "fitgirl",
      "cover_url": "http://s01.riotpixels.net/data/b9/0d/b90deb78-2143-4aa7-90fd-d937fbced492.jpg",
      "repack_size": "15.1/15.2 GB"
    },
    {
      "id": "bb61868bed2c861773f3f3c23434543b",
      "title": "Barbie Project Friendship",
      "url": "https://fitgirl-repacks.site/barbie-project-friendship/",
      "provider": "fitgirl",
      "cover_url": "https://i5.imageban.ru/out/2025/01/02/1e85ffad57b915c567c98bf445485a33.jpg",
      "repack_size": "1.4 GB"
    },
    {
      "id": "bb7ee656a41c586bac65ad0e07f11014",
      "title": "F1 2018: Headline Edition – v1.16 + DLC",
      "url": "https://fitgirl-repacks.site/f1-2018/",
      "provider": "fitgirl",
      "cover_url": "http://s01.riotpixels.net/data/41/a4/41a4df02-71c2-4987-94e7-0876031cdcef.jpg",
      "repack_size": "from 15.2 GB [Selective Download]"
    },
    {
      "id": "bb86a8f5625614df2da040bdefc11c2e",
      "title": "Blind Fate: Edo no Yami – v1.0.1",
      "url": "https://fitgirl-repacks.site/blind-fate-edo-no-yami/",
      "provider": "fitgirl",
      "cover_url": "https://i4.imageban.ru/out/2022/09/16/cb48feb26c41834826e358a64a0b5e15.jpg",
      "repack_size": "GB"
    },
    {
      "id": "bb9aaf672ca1968cd3bb2368a3d23d78",
      "title": "Mordheim: City of the Damned v1.3.4.2 + 5 DLC",
      "url": "https://fitgirl-repacks.site/mordheim-city-of-the-damned-v1-3-4-2-5-dlc/",
      "provider": "fitgirl",
      "cover_url": "http://i67.fastpic.ru/big/2015/1123/e7/78ae90ccbf37640be2730386a0661ce7.jpg",
      "repack_size": "3/3.1 GB [Selective Download]"
    },
    {
      "id": "bba6e0f03417787164d006d9515a9c2b",
      "title": "Lost Eidolons: Digital Deluxe Edition – v1.5.4.R29.eb474865 + DLC + Bonus Content",
      "url": "https://fitgirl-repacks.site/lost-eidolons/",
      "provider": "fitgirl",
      "cover_url": "https://i6.imageban.ru/out/2022/10/15/4dba15f23f6c2b5f1d462674e536b050.jpg",
      "repack_size": "7.6/7.8 GB"
    },
    {
      "id": "bbaf7090eaca2d180ff00bbd166e63a6",
      "title": "Heroes of Science and Fiction Repack Updated",
      "url": "https://fitgirl-repacks.site/heroes-of-science-and-fiction-repack-updated/",
      "provider": "fitgirl",
      "cover_url": "",
      "repack_size": "Unknown"
    },
    {
      "id": "bbaf7a3aeb8469cdbf38bdb6ed164275",
      "title": "Pine",
      "url": "https://fitgirl-repacks.site/pine/",
      "provider": "fitgirl",
      "cover_url": "http://s01.riotpixels.net/data/74/4b/744bd0e1-f88f-48e5-96d3-45368b289a01.jpg",
      "repack_size": "1.4 GB"
    },
    {
      "id": "bbb299a70a9e664682947f4717fddd85",
      "title": "Super Robot Wars V + 2 DLCs",
      "url": "https://fitgirl-repacks.site/super-robot-wars-v/",
      "provider": "fitgirl",
      "cover_url": "http://s01.riotpixels.net/data/c8/f5/c8f594fc-fb1b-4f2a-929d-12687e085d20.jpg",
      "repack_size": "4.5 GB"
    },
    {
      "id": "bbb320f4d3c43f189c60c5d73defc58d",
      "title": "Captain Contraption’s Chocolate Factory – Soundtrack Bundle, v1.22 + Bonus OST",
      "url": "https://fitgirl-repacks.site/captain-contraptions-chocolate-factory/",
      "provider": "fitgirl",
      "cover_url": "https://i3.imageban.ru/out/2024/11/06/4f36cfe833cb2a30bbdb46a5b0b52866.jpg",
      "repack_size": "281 MB"
    },
    {
      "id": "bbba4d2a145b8e7584638a81cf90c905",
      "title": "HUMANKIND: Premium Edition – v1.0.24.4218 + 19 DLCs/Bonuses",
      "url": "https://fitgirl-repacks.site/humankind/",
      "provider": "fitgirl",
      "cover_url": "https://i6.imageban.ru/out/2021/08/17/76684cfb7f94a0d94018a876eedf4b14.jpg",
      "repack_size": "from 7.6 GB [Selective Download]"
    },
    {
      "id": "bbba53badaa0df9dd6465603707e60d1",
      "title": "Mandragora: Whispers of the Witch Tree – Digital Deluxe Edition, v1.2.4.2147 + 9 DLCs/Bonuses",
      "url": "https://fitgirl-repacks.site/mandragora-whispers-of-the-witch-tree/",
      "provider": "fitgirl",
      "cover_url": "https://i7.imageban.ru/out/2025/04/18/2d14f66cc7996ff98951f2f5cee18232.jpg",
      "repack_size": "11.4/11.6 GB"
    },
    {
      "id": "bbf952ca936fae576e31bb25cd168619",
      "title": "Solarix",
      "url": "https://fitgirl-repacks.site/solarix/",
      "provider": "fitgirl",
      "cover_url": "http://i59.fastpic.ru/big/2015/0503/0b/f6a068d1c69c79348b243e1140c67d0b.jpg",
      "repack_size": "1,6 GB"
    }
  ]
}