{
  "page": 19,
  "total_pages": 233,
  "items": [
    {
      "id": "12cb80a7e851dae50a43acc9c70db6b9",
      "title": "Fire Commander",
      "url": "https://fitgirl-repacks.site/fire-commander/",
      "provider": "fitgirl",
      "cover_url": "https://i6.imageban.ru/out/2022/07/29/bc125bd8b4b28328328b21c3b14a5b50.jpg",
      "repack_size": "3/3.1 GB"
    },
    {
      "id": "12d0b7c1b1329cd0e3ea6ad6bc0eec59",
      "title": "Gloomy Eyes: Deluxe Edition + Bonus OST",
      "url": "https://fitgirl-repacks.site/gloomy-eyes/",
      "provider": "fitgirl",
      "cover_url": "https://i2.imageban.ru/out/2025/09/17/08551462a67c0d60dc8bdebb2e3b3104.jpg",
      "repack_size": "2.4/2.7 GB"
    },
    {
      "id": "1307505fea8d40e873c67cf8eebb46af",
      "title": "Cafe Owner Simulator – v1.4.105 + Farm DLC",
      "url": "https://fitgirl-repacks.site/cafe-owner-simulator/",
      "provider": "fitgirl",
      "cover_url": "https://i3.imageban.ru/out/2022/12/07/8618b1582f9f95ba40cb4cd9ac9f5093.jpg",
      "repack_size": "3.3 GB"
    },
    {
      "id": "1319bee58342013d58fa02fa4904e7d2",
      "title": "LEGO Marvel’s Avengers v1.0.0.28133 + 11 DLC",
      "url": "https://fitgirl-repacks.site/lego-marvels-avengers-v1-0-0-28133-11-dlc/",
      "provider": "fitgirl",
      "cover_url": "http://i80.fastpic.ru/big/2016/0614/dd/66c4394032823425b866406a6a9edcdd.jpg",
      "repack_size": "from 5.7 GB [Selective Download]"
    },
    {
      "id": "1330221127a598bf6a8d5a62b2716fef",
      "title": "I Hate This Place – v1.0.13_15856",
      "url": "https://fitgirl-repacks.site/i-hate-this-place/",
      "provider": "fitgirl",
      "cover_url": "https://i3.imageban.ru/out/2026/01/30/2f698444b359cd7894581ae57cef000b.jpg",
      "repack_size": "1.2 GB"
    },
    {
      "id": "133fcd1c5f7ed546610e65b8f110ba16",
      "title": "Brutal Rifters",
      "url": "https://fitgirl-repacks.site/brutal-rifters/",
      "provider": "fitgirl",
      "cover_url": "https://i3.imageban.ru/out/2022/02/20/40ba9146ca45143d0a326d0359046d57.jpg",
      "repack_size": "8.9 GB"
    },
    {
      "id": "1346273edd1b462935353e5039257747",
      "title": "Recycling Center Simulator – v1.7.1 + DLC",
      "url": "https://fitgirl-repacks.site/recycling-center-simulator/",
      "provider": "fitgirl",
      "cover_url": "https://i8.imageban.ru/out/2024/12/24/dde27526505acc90dd4b5bd03b789c62.jpg",
      "repack_size": "2 GB"
    },
    {
      "id": "1346d47072bb72f0e8a08b490b448283",
      "title": "What The Duck",
      "url": "https://fitgirl-repacks.site/what-the-duck/",
      "provider": "fitgirl",
      "cover_url": "https://i4.imageban.ru/out/2023/11/20/5ab23b09da8ff670bc9ff70e0b769703.jpg",
      "repack_size": "1.5 GB"
    },
    {
      "id": "134d80ea01f18bb9611e62ff6f0e211f",
      "title": "NEDRA",
      "url": "https://fitgirl-repacks.site/nedra/",
      "provider": "fitgirl",
      "cover_url": "https://i4.imageban.ru/out/2025/06/26/2c733f88675b0f395a88d385dcee9db7.jpg",
      "repack_size": "5.4 GB"
    },
    {
      "id": "1352982a1805d6805aebdd103b1b07da",
      "title": "Granny Remake – v3.0.1 + Windows 7 Fix",
      "url": "https://fitgirl-repacks.site/granny-remake/",
      "provider": "fitgirl",
      "cover_url": "https://i1.imageban.ru/out/2023/07/23/5f007418f54242870998541a5798301e.jpg",
      "repack_size": "GB"
    },
    {
      "id": "1357a7da9cb257ae8e6bfcdcee79215d",
      "title": "StarFlint the BlackHole Prophecy – v1.03 + Cosmetics DLC",
      "url": "https://fitgirl-repacks.site/starflint-the-blackhole-prophecy/",
      "provider": "fitgirl",
      "cover_url": "https://i6.imageban.ru/out/2022/07/11/c478d7daae0ac7191c594ba28d21c9aa.jpg",
      "repack_size": "1.5 GB"
    },
    {
      "id": "135f22b5f1d91dda398599653710864b",
      "title": "Cybermere – v1.19.2",
      "url": "https://fitgirl-repacks.site/cybermere/",
      "provider": "fitgirl",
      "cover_url": "https://i1.imageban.ru/out/2022/01/07/e7576f6d8806a8b0ad9d4d637601d8a5.jpg",
      "repack_size": "2.5 GB"
    },
    {
      "id": "1361347de7b00ae1b1f55dbfca8e8c66",
      "title": "Dinobreak",
      "url": "https://fitgirl-repacks.site/dinobreak/",
      "provider": "fitgirl",
      "cover_url": "https://i7.imageban.ru/out/2023/10/13/6d5351824e5022d7162107a2cfaec217.jpg",
      "repack_size": "4.4 GB"
    },
    {
      "id": "13865d69ade1aca8ca6d21790b668779",
      "title": "Rise of Gun – v3.0.0 (Release)",
      "url": "https://fitgirl-repacks.site/rise-of-gun/",
      "provider": "fitgirl",
      "cover_url": "https://i6.imageban.ru/out/2024/03/27/d77252e7412948fec5718895ff40bf0a.jpg",
      "repack_size": "437 MB"
    },
    {
      "id": "138b637b80997dd6b939978f2b1d81e5",
      "title": "Guilty Gear 2: Overture",
      "url": "https://fitgirl-repacks.site/guilty-gear-2-overture/",
      "provider": "fitgirl",
      "cover_url": "http://i76.fastpic.ru/big/2016/0401/d0/2c9f66e3ee3cd63c7d5e5f2bdef741d0.jpg",
      "repack_size": "975 MB"
    },
    {
      "id": "138dc9e4baba37e37f735d0bb79c23b7",
      "title": "Bootlegger’s Mafia Racing Story",
      "url": "https://fitgirl-repacks.site/bootleggers-mafia-racing-story/",
      "provider": "fitgirl",
      "cover_url": "https://i6.imageban.ru/out/2024/01/06/b71fdfb72a275326c4883c8a841805a5.jpg",
      "repack_size": "1.1 GB"
    },
    {
      "id": "1397b20db6d17fa9040b5767c0d1c364",
      "title": "Is It Wrong to Try to Pick Up Girls in a Dungeon? Infinite Combate – Builds 5355189 (CODEX) + 5402416",
      "url": "https://fitgirl-repacks.site/is-it-wrong-to-try-to-pick-up-girls-in-a-dungeon-infinite-combate/",
      "provider": "fitgirl",
      "cover_url": "http://s01.riotpixels.net/data/d2/96/d29625e7-830e-4e01-bdfe-49147aa42fa1.jpg",
      "repack_size": "from 1.5 GB [Selective Download]"
    },
    {
      "id": "13ade6dad5b0d89023228f24b7550f47",
      "title": "Pandemic Train – v1.2.0",
      "url": "https://fitgirl-repacks.site/pandemic-train/",
      "provider": "fitgirl",
      "cover_url": "https://i2.imageban.ru/out/2023/10/21/8dae857db3ccc190803ff77a50ce6af4.jpg",
      "repack_size": "3.2 GB"
    },
    {
      "id": "13b244b1c54d0f2f391c082db601f58c",
      "title": "Void: Dementia – v1.0.7",
      "url": "https://fitgirl-repacks.site/void-dementia/",
      "provider": "fitgirl",
      "cover_url": "https://i5.imageban.ru/out/2022/07/13/3022d499f51dc0e4a5eda1c5eb2ec520.jpg",
      "repack_size": "1.8 GB"
    },
    {
      "id": "13bd49f675819e92a8d54c3ea2020665",
      "title": "PROHIBEAST – v0.9.075",
      "url": "https://fitgirl-repacks.site/prohibeast/",
      "provider": "fitgirl",
      "cover_url": "https://i4.imageban.ru/out/2026/06/05/99fed21fd7bfaf4f5a984c8ad712f8f3.jpg",
      "repack_size": "3.9 GB"
    },
    {
      "id": "13c03c59892b54e00655012631a4256e",
      "title": "Aquascapers – v2024.18.4 (Release)",
      "url": "https://fitgirl-repacks.site/aquascapers/",
      "provider": "fitgirl",
      "cover_url": "https://i2.imageban.ru/out/2024/05/06/1986254727e88d5a378851b8000018ad.jpg",
      "repack_size": "3.9 GB"
    },
    {
      "id": "13c8a796482fb58731031c7fd275157e",
      "title": "LiBER",
      "url": "https://fitgirl-repacks.site/liber/",
      "provider": "fitgirl",
      "cover_url": "https://i2.imageban.ru/out/2022/01/12/0aeab6673940a58180fcc306bd02490a.jpg",
      "repack_size": "10.1 GB"
    },
    {
      "id": "13cae594d25d359b64c01e0d49543dfc",
      "title": "AO International Tennis – v1.0.1588",
      "url": "https://fitgirl-repacks.site/ao-international-tennis/",
      "provider": "fitgirl",
      "cover_url": "http://s01.riotpixels.net/data/53/7d/537d16c2-ff9e-4a56-a5f0-301ab54f7177.jpg",
      "repack_size": "4.5 GB"
    },
    {
      "id": "13ccf3e950146da9c73aa7977ed67234",
      "title": "The Descendant: Full Season (Episodes 1-5)",
      "url": "https://fitgirl-repacks.site/descendant-full-season-episodes-1-5/",
      "provider": "fitgirl",
      "cover_url": "http://s01.riotpixels.net/data/ee/09/ee09f21f-74f9-4899-a994-0d81956f0311.jpg",
      "repack_size": "4 GB"
    },
    {
      "id": "13ce931e1da9d5c1ce83bc7daadc909e",
      "title": "REYNATIS: Ultimate Edition, v1.0.7 + 10 DLCs",
      "url": "https://fitgirl-repacks.site/reynatis/",
      "provider": "fitgirl",
      "cover_url": "https://i6.imageban.ru/out/2024/09/28/abc319b1f43fd4e8a55af39e33469aed.jpg",
      "repack_size": "3.6~4.1 GB"
    },
    {
      "id": "13d05a1069257eb93da294b7f80cb437",
      "title": "Skeleton Crew – v1.0.2 (x64/x86)",
      "url": "https://fitgirl-repacks.site/skeleton-crew/",
      "provider": "fitgirl",
      "cover_url": "https://i6.imageban.ru/out/2022/06/18/af464318e025ba89ad0863d1e83ac43f.jpg",
      "repack_size": "1.2 GB"
    },
    {
      "id": "13d4028fa4b2331405b4a5831715d0b9",
      "title": "Naheulbeuk’s Dungeon Master: Steward Edition – v1.2.213.26146 + Bonus Soundtrack",
      "url": "https://fitgirl-repacks.site/naheulbeuks-dungeon-master/",
      "provider": "fitgirl",
      "cover_url": "https://i4.imageban.ru/out/2023/11/29/431db3aa15a4abe9bb36b0f55a2a2364.jpg",
      "repack_size": "from 2.1 GB [Selective Download]"
    },
    {
      "id": "13d55c5550fcfb96f673e21168c2b2a0",
      "title": "Event[0]",
      "url": "https://fitgirl-repacks.site/event0/",
      "provider": "fitgirl",
      "cover_url": "http://s01.riotpixels.net/data/db/55/db55a398-1965-451a-ace9-07cafa495b58.jpg",
      "repack_size": "1.5 GB"
    },
    {
      "id": "13d72cfbc30d945dc466225b3f8070aa",
      "title": "The Silver Case 2425 + Yuzu/Ryujinx Emus for PC",
      "url": "https://fitgirl-repacks.site/the-silver-case-2425/",
      "provider": "fitgirl",
      "cover_url": "https://i1.imageban.ru/out/2021/07/25/46a27c11a0a98b3ccd231a40c7a325ed.jpg",
      "repack_size": "3.5 GB"
    },
    {
      "id": "13d977311ca35823db3d03786e1914b4",
      "title": "Stellar Outpost Commander",
      "url": "https://fitgirl-repacks.site/stellar-outpost-commander/",
      "provider": "fitgirl",
      "cover_url": "https://i6.imageban.ru/out/2025/05/02/64440172678130a5a2e3ecf048502978.jpg",
      "repack_size": "686 MB"
    }
  ]
}